{
  "operations": [
    {
      "id": "testId1",
      "type": "Expense",
      "price": 30,
      "category": "Products",
      "date": "09.05.2023",
      "payment": "Card",
      "comment": "comment"
    },
    {
      "id": "testId2",
      "type": "Expense",
      "price": 20,
      "category": "Products",
      "date": "09.05.2023",
      "payment": "Cash",
      "comment": null
    },
    {
      "id": "testId3",
      "type": "Expense",
      "price": 10,
      "category": "Products",
      "date": "09.05.2023",
      "payment": "Card",
      "comment": "comment"
    },
    {
      "id": "67da88cc-df50-413b-a3c4-37ff02c0f886",
      "type": "Expense",
      "price": "34",
      "category": "Transport",
      "date": "Wed May 10 2023 13:59:32 GMT+0300 (за східноєвропейським літнім часом)",
      "payment": "Card",
      "comment": null
    },
    {
      "id": "50fb5b84-d45f-414f-8d52-13b1d43b1532",
      "type": "Expense",
      "price": "345",
      "category": "Gifts",
      "date": "Wed May 10 2023 14:00:32 GMT+0300 (за східноєвропейським літнім часом)",
      "payment": "Cash",
      "comment": null
    },
    {
      "id": "30eed024-6e67-4e1a-b858-577af05a1230",
      "type": "Expense",
      "price": "334543",
      "category": "Transport",
      "date": "Wed May 10 2023 14:01:59 GMT+0300 (за східноєвропейським літнім часом)",
      "payment": "Card",
      "comment": null
    },
    {
      "id": "5a250c82-f759-4cc3-b2b3-8bd727914a5b",
      "type": "Expense",
      "price": "4534",
      "category": "Gifts",
      "date": "Wed May 10 2023 14:04:31 GMT+0300 (за східноєвропейським літнім часом)",
      "payment": "Card",
      "comment": null
    },
    {
      "id": "8831077a-d2de-4319-85e1-cb6ce7dc5aaf",
      "type": "Expense",
      "price": "111111",
      "category": "Gifts",
      "date": "Wed May 10 2023 14:27:15 GMT+0300 (за східноєвропейським літнім часом)",
      "payment": "Cash",
      "comment": null
    }
  ]
}